modforge_cli/__init__.py
modforge_cli/__main__.py
modforge_cli/__version__.py
modforge_cli/api/__init__.py
modforge_cli/api/modrinth.py
modforge_cli/cli.py
modforge_cli/core/__init__.py
modforge_cli/core/downloader.py
modforge_cli/core/models.py
modforge_cli/core/policy.py
modforge_cli/core/resolver.py
modforge_cli/core/utils.py
modforge_cli-0.1.8.dist-info/METADATA
modforge_cli-0.1.8.dist-info/WHEEL
modforge_cli-0.1.8.dist-info/entry_points.txt
modforge_cli-0.1.8.dist-info/licenses/LICENSE
modforge_cli-0.1.8.dist-info/RECORD
